setup.py
groundhogday/__init__.py
groundhogday/groundhogday.py
groundhogday/retry_with_airbrake.py
groundhogday/retry_with_sentry.py
groundhogday.egg-info/PKG-INFO
groundhogday.egg-info/SOURCES.txt
groundhogday.egg-info/dependency_links.txt
groundhogday.egg-info/requires.txt
groundhogday.egg-info/top_level.txt
test/__init__.py
test/test_groundhogday.py