Metadata-Version: 1.0
Name: groundhogday
Version: 1.0.0
Summary: GroundhogDay lets you repeat an operation until you get it right.
Home-page: https://github.com/bcoe/groundhogday
Author: Benjamin Coe
Author-email: ben@attachments.me
License: UNKNOWN
Platform: UNKNOWN
